pineapple_spark-1.1.0.dist-info/WHEEL
pineapple_spark-1.1.0.dist-info/METADATA
pineapple_spark-1.1.0.dist-info/top_level.txt
pineapple_spark-1.1.0.dist-info/RECORD
sedona/exceptions.py
sedona/version.py
sedona/__init__.py
sedona/sql/dataframe_api.py
sedona/sql/exceptions.py
sedona/sql/st_constructors.py
sedona/sql/st_functions.py
sedona/sql/st_aggregates.py
sedona/sql/__init__.py
sedona/sql/st_predicates.py
sedona/sql/types.py
sedona/utils/prep.py
sedona/utils/geomserde_speedup.cpython-36m-x86_64-linux-gnu.so
sedona/utils/geometry_serde_general.py
sedona/utils/geometry_serde.py
sedona/utils/adapter.py
sedona/utils/ddcel_parser.py
sedona/utils/geometry_adapter.py
sedona/utils/serde.py
sedona/utils/decorators.py
sedona/utils/meta.py
sedona/utils/binary_parser.py
sedona/utils/__init__.py
sedona/utils/spatial_rdd_parser.py
sedona/utils/jvm.py
sedona/utils/abstract_parser.py
sedona/utils/types.py
sedona/register/java_libs.py
sedona/register/geo_registrator.py
sedona/register/__init__.py
sedona/core/__init__.py
sedona/core/utils.py
sedona/core/enums/ddcel_enums.py
sedona/core/enums/file_data_splitter.py
sedona/core/enums/index_type.py
sedona/core/enums/grid_type.py
sedona/core/enums/join_build_side.py
sedona/core/enums/__init__.py
sedona/core/enums/spatial.py
sedona/core/jvm/config.py
sedona/core/jvm/translate.py
sedona/core/jvm/__init__.py
sedona/core/jvm/abstract.py
sedona/core/geom/circle.py
sedona/core/geom/__init__.py
sedona/core/geom/envelope.py
sedona/core/spatialOperator/rdd.py
sedona/core/spatialOperator/join_query.py
sedona/core/spatialOperator/join_query_raw.py
sedona/core/spatialOperator/join_params.py
sedona/core/spatialOperator/range_query.py
sedona/core/spatialOperator/__init__.py
sedona/core/spatialOperator/sgpac_query.py
sedona/core/spatialOperator/quadtree_ddcel.py
sedona/core/spatialOperator/knn_query.py
sedona/core/spatialOperator/range_query_raw.py
sedona/core/SpatialRDD/rectangle_rdd.py
sedona/core/SpatialRDD/point_rdd.py
sedona/core/SpatialRDD/spatial_rdd_factory.py
sedona/core/SpatialRDD/__init__.py
sedona/core/SpatialRDD/circle_rdd.py
