Metadata-Version: 2.1
Name: pineapple-spark
Version: 1.1.0
Summary: Pineapple is an extension of Apache Sedona for processing large-scale complex spatial queries
Home-page: https://github.com/laila-abdelhafeez/pineapple
Author: Laila Abdelhafeez
Author-email: labde005@ucr.edu
License: UNKNOWN
Project-URL: Documentation, https://https://github.com/laila-abdelhafeez/pineapple
Project-URL: Source code, https://github.com/laila-abdelhafeez/pineapple
Project-URL: Bug Reports, https://github.com/laila-abdelhafeez/pineapple
Platform: UNKNOWN
Classifier: Programming Language :: Python :: 3
Classifier: License :: OSI Approved :: Apache Software License
Requires-Python: >=3.6
Requires-Dist: attrs
Requires-Dist: shapely (>=1.7.0)
Provides-Extra: spark
Requires-Dist: pyspark (>=2.3.0) ; extra == 'spark'
